[
  {
    "id": "featured_domination_translator_domination_translator_09_tee_hit_ton",
    "type": "article-webpage",
    "title": "Tee Hit Ton Indians v. United States (1955) - Domination Translator Series - Part 9",
    "URL": "https://outcome.doctrineofdiscovery.org/featured/domination-translator/domination-translator-09/tee-hit-ton/",
    "author": [
      {
        "family": "Newcomb",
        "given": "Steven T."
      }
    ],
    "issued": {
      "date-parts": [
        [
          2026
        ]
      ]
    },
    "DOI": "https://doctrineofdiscovery.org/blog/domination/tee-hit-ton/"
  }
]
