[
  {
    "id": "ecozoic_arnold_bigtree",
    "type": "article-webpage",
    "title": "The Haudenosaunee (Iroquois) Great Binding Peace",
    "URL": "https://outcome.doctrineofdiscovery.org/ecozoic/essay1/haudenosaunee-great-binding-peace/",
    "author": [
      {
        "family": "Arnold",
        "given": "Philip P."
      },
      {
        "family": "Bigtree",
        "given": "Sandra"
      }
    ],
    "issued": {
      "date-parts": [
        [
          2025
        ]
      ]
    },
    "DOI": "https://ecozoicstudies.org/new_ecozoic_reader/the-haudenosaunee-iroquois-great-binding-peace/"
  }
]
